<?xml version="1.0" encoding="utf-8"?>
<papers>
  <paper>
    <metadata/>
    <fulltext>
      <literature/>
      <text value="authorsrus"/>
      <braces>
        <text value="{}"/>
      </braces>
      <command value="\raggedleft"/>
      <command value="\Large"/>
      <command value="\bf"/>
      <text value="О"/>
      <text value="Б"/>
      <text value="А"/>
      <text value="В"/>
      <text value="Т"/>
      <text value="О"/>
      <text value="Р"/>
      <text value="А"/>
      <text value="Х"/>
      <command value="\vskip">
        <braces>
          <text value="17pt"/>
        </braces>
      </command>
      <command value="\hrule"/>
      <command value="\par"/>
      <command value="\vskip">
        <braces>
          <text value="21pt plus 8pt minus 3pt"/>
        </braces>
        <braces/>
      </command>
      <command value="\label">
        <braces>
          <braces>
            <text value="{}"/>
            <text value="st"/>
            <command value="\stat">
              <braces/>
            </command>
          </braces>
        </braces>
      </command>
      <text value="ОБ АВТОРАХ"/>
      <command value="\vspace*">
        <braces>
          <braces>
            <text value="{}"/>
            <text value="36pt"/>
          </braces>
        </braces>
        <braces/>
      </command>
      <command value="\begin">
        <braces>
          <braces>
            <text value="{}"/>
            <text value="2"/>
          </braces>
        </braces>
        <braces/>
      </command>
      <command value="\noindent">
        <braces>
          <text value="\noindent"/>
        </braces>
      </command>
      <command value="\textbf">
        <braces>
          <text value="\textbf{}"/>
        </braces>
        <text value="Бенинг Владимир Евгеньевич"/>
      </command>
      <text value="(р."/>
      <command value="\specialsymbol">
        <braces>
          <text value="~---"/>
        </braces>
      </command>
      <text value="доктор физико-математических наук, профессор кафедры математической статистики факультета вычислительной математики и кибернетики Московского"/>
      <command value="\linebreak">
        <braces>
          <text value="\linebreak"/>
        </braces>
      </command>
      <text value="государственного университета им."/>
      <text value="М."/>
      <text value="В. Ломоносова; старший научный сотрудник ИПИ РАН"/>
      <command value="\vspace*">
        <braces>
          <braces>
            <text value="{}"/>
            <text value="4pt"/>
          </braces>
        </braces>
        <braces/>
      </command>
      <command value="\noindent">
        <braces>
          <text value="\noindent"/>
        </braces>
      </command>
      <command value="\textbf">
        <braces>
          <text value="\textbf{}"/>
        </braces>
        <text value="Бородина Александра Валентиновна"/>
      </command>
      <text value="(р."/>
      <command value="\specialsymbol">
        <braces>
          <text value="~---"/>
        </braces>
      </command>
      <text value="младший научный сотрудник Института прикладных математических исследований КарНЦ РАН"/>
      <command value="\vspace*">
        <braces>
          <braces>
            <text value="{}"/>
            <text value="4pt"/>
          </braces>
        </braces>
        <braces/>
      </command>
      <command value="\noindent">
        <braces>
          <text value="\noindent"/>
        </braces>
      </command>
      <command value="\textbf">
        <braces>
          <text value="\textbf{}"/>
        </braces>
        <text value="Галиева Нургуль Кадыржановна"/>
      </command>
      <text value="(р."/>
      <command value="\specialsymbol">
        <braces>
          <text value="~---"/>
        </braces>
      </command>
      <text value="преподаватель Казахстанского филиала Московского государственного университета им."/>
      <text value="М."/>
      <text value="В. Ломоносова"/>
      <command value="\vspace*">
        <braces>
          <braces>
            <text value="{}"/>
            <text value="4pt"/>
          </braces>
        </braces>
        <braces/>
      </command>
      <command value="\noindent">
        <braces>
          <text value="\noindent"/>
        </braces>
      </command>
      <command value="\textbf">
        <braces>
          <text value="\textbf{}"/>
        </braces>
        <text value="Галина Ирина Владимировна"/>
      </command>
      <text value="(р."/>
      <command value="\specialsymbol">
        <braces>
          <text value="~---"/>
        </braces>
      </command>
      <text value="старший научный сотрудник ИПИ РАН"/>
      <command value="\vspace*">
        <braces>
          <braces>
            <text value="{}"/>
            <text value="4pt"/>
          </braces>
        </braces>
        <braces/>
      </command>
      <command value="\noindent">
        <braces>
          <text value="\noindent"/>
        </braces>
      </command>
      <command value="\textbf">
        <braces>
          <text value="\textbf{}"/>
        </braces>
        <text value="Закс Лилия Михайловна"/>
      </command>
      <text value="(р."/>
      <command value="\specialsymbol">
        <braces>
          <text value="~---"/>
        </braces>
      </command>
      <text value="главный специалист отдела моделирования и математической статистики Альфа-банка"/>
      <command value="\vspace*">
        <braces>
          <braces>
            <text value="{}"/>
            <text value="4pt"/>
          </braces>
        </braces>
        <braces/>
      </command>
      <command value="\noindent">
        <braces>
          <text value="\noindent"/>
        </braces>
      </command>
      <command value="\textbf">
        <braces>
          <text value="\textbf{}"/>
        </braces>
        <text value="Зализняк Анна Андреевна"/>
      </command>
      <text value="(р."/>
      <command value="\specialsymbol">
        <braces>
          <text value="~---"/>
        </braces>
      </command>
      <text value="доктор филологических наук, ведущий научный сотрудник ИЯз РАН и ИПИ РАН"/>
      <command value="\vspace*">
        <braces>
          <braces>
            <text value="{}"/>
            <text value="4pt"/>
          </braces>
        </braces>
        <braces/>
      </command>
      <command value="\noindent">
        <braces>
          <text value="\noindent"/>
        </braces>
      </command>
      <command value="\textbf">
        <braces>
          <text value="\textbf{}"/>
        </braces>
        <text value="Зацман Игорь Моисеевич"/>
      </command>
      <text value="(р."/>
      <command value="\specialsymbol">
        <braces>
          <text value="~---"/>
        </braces>
      </command>
      <text value="доктор технических наук, заведующий отделом ИПИ РАН"/>
      <command value="\vspace*">
        <braces>
          <braces>
            <text value="{}"/>
            <text value="4pt"/>
          </braces>
        </braces>
        <braces/>
      </command>
      <command value="\noindent">
        <braces>
          <text value="\noindent"/>
        </braces>
      </command>
      <command value="\textbf">
        <braces>
          <text value="\textbf{}"/>
        </braces>
        <text value="Зейфман Александр Израилевич"/>
      </command>
      <text value="(р."/>
      <command value="\specialsymbol">
        <braces>
          <text value="~---"/>
        </braces>
      </command>
      <text value="доктор физико-математических наук, профессор, декан факультета прикладной математики и компьютерных технологий Вологодского государственного педагогического университета; старший научный сотрудник ИПИ РАН, ведущий научный сотрудник ВНКЦ ЦЭМИ РАН"/>
      <command value="\vspace*">
        <braces>
          <braces>
            <text value="{}"/>
            <text value="4pt"/>
          </braces>
        </braces>
        <braces/>
      </command>
      <command value="\noindent">
        <braces>
          <text value="\noindent"/>
        </braces>
      </command>
      <command value="\textbf">
        <braces>
          <text value="\textbf{}"/>
        </braces>
        <text value="Козеренко Елена Борисовна"/>
      </command>
      <text value="(р."/>
      <command value="\specialsymbol">
        <braces>
          <text value="~---"/>
        </braces>
      </command>
      <text value="кандидат филологических наук, заведующая лабораторией ИПИ РАН"/>
      <command value="\vspace*">
        <braces>
          <braces>
            <text value="{}"/>
            <text value="4pt"/>
          </braces>
        </braces>
        <braces/>
      </command>
      <command value="\noindent">
        <braces>
          <text value="\noindent"/>
        </braces>
      </command>
      <command value="\textbf">
        <braces>
          <text value="\textbf{}"/>
        </braces>
        <text value="Королев Виктор Юрьевич"/>
      </command>
      <text value="(р."/>
      <command value="\specialsymbol">
        <braces>
          <text value="~---"/>
        </braces>
      </command>
      <text value="доктор физико-математических наук, профессор кафедры математической статистики факультета вычислительной математики и кибернетики Московского"/>
      <command value="\linebreak">
        <braces>
          <text value="\linebreak"/>
        </braces>
      </command>
      <text value="государственного университета им."/>
      <text value="М."/>
      <text value="В. Ломоносова; ведущий научный сотрудник ИПИ РАН"/>
      <command value="\vspace*">
        <braces>
          <braces>
            <text value="{}"/>
            <text value="4pt"/>
          </braces>
        </braces>
        <braces/>
      </command>
      <command value="\noindent">
        <braces>
          <text value="\noindent"/>
        </braces>
      </command>
      <command value="\textbf">
        <braces>
          <text value="\textbf{}"/>
        </braces>
        <text value="Кудрявцев Алексей Андреевич"/>
      </command>
      <text value="(р."/>
      <command value="\specialsymbol">
        <braces>
          <text value="~---"/>
        </braces>
      </command>
      <text value="кандидат физико-математических наук, старший преподаватель кафедры математической статистики факультета вычислительной математики и кибернетики Московского государственного университета им."/>
      <text value="М."/>
      <text value="В. Ломоносова"/>
      <command value="\vspace*">
        <braces>
          <braces>
            <text value="{}"/>
            <text value="4pt"/>
          </braces>
        </braces>
        <braces/>
      </command>
      <command value="\noindent">
        <braces>
          <text value="\noindent"/>
        </braces>
      </command>
      <command value="\textbf">
        <braces>
          <text value="\textbf{}"/>
        </braces>
        <text value="Кузнецов Игорь Петрович"/>
      </command>
      <text value="(р."/>
      <command value="\specialsymbol">
        <braces>
          <text value="~---"/>
        </braces>
      </command>
      <text value="доктор технических наук, главный научный сотрудник ИПИ РАН"/>
      <command value="\vspace*">
        <braces>
          <braces>
            <text value="{}"/>
            <text value="4pt"/>
          </braces>
        </braces>
        <braces/>
      </command>
      <command value="\noindent">
        <braces>
          <text value="\noindent"/>
        </braces>
      </command>
      <command value="\textbf">
        <braces>
          <text value="\textbf{}"/>
        </braces>
        <text value="Купалов-Ярополк Игорь Константинович"/>
      </command>
      <text value="(р."/>
      <command value="\specialsymbol">
        <braces>
          <text value="~---"/>
        </braces>
      </command>
      <text value="заместитель начальника отдела Института точной механики и вычислительной техники им."/>
      <text value="С."/>
      <text value="А. Лебедева РАН"/>
      <command value="\vspace*">
        <braces>
          <braces>
            <text value="{}"/>
            <text value="4pt"/>
          </braces>
        </braces>
        <braces/>
      </command>
      <command value="\noindent">
        <braces>
          <text value="\noindent"/>
        </braces>
      </command>
      <command value="\textbf">
        <braces>
          <text value="\textbf{}"/>
        </braces>
        <text value="Луазо Сильвен"/>
      </command>
      <text value="(р."/>
      <command value="\specialsymbol">
        <braces>
          <text value="~---"/>
        </braces>
      </command>
      <text value="доктор философии (PhD), доцент, Университет Париж-13, лаборатория лексики, словарей и информатики НЦНИ"/>
      <command value="\vspace*">
        <braces>
          <braces>
            <text value="{}"/>
            <text value="4pt"/>
          </braces>
        </braces>
        <braces/>
      </command>
      <command value="\noindent">
        <braces>
          <text value="\noindent"/>
        </braces>
      </command>
      <command value="\textbf">
        <braces>
          <text value="\textbf{}"/>
        </braces>
        <text value="Малашенко Юрий Евгеньевич"/>
      </command>
      <text value="(р."/>
      <command value="\specialsymbol">
        <braces>
          <text value="~---"/>
        </braces>
      </command>
      <text value="доктор физико-математических наук, заведующий сектором Вычислительного центра им."/>
      <text value="А."/>
      <text value="А. Дородницына РАН"/>
      <command value="\vspace*">
        <braces>
          <braces>
            <text value="{}"/>
            <text value="4pt"/>
          </braces>
        </braces>
        <braces/>
      </command>
      <command value="\noindent">
        <braces>
          <text value="\noindent"/>
        </braces>
      </command>
      <command value="\textbf">
        <braces>
          <text value="\textbf{}"/>
        </braces>
        <text value="Морозов Евсей Викторович"/>
      </command>
      <text value="(р."/>
      <command value="\specialsymbol">
        <braces>
          <text value="~---"/>
        </braces>
      </command>
      <text value="доктор физико-математических наук, профессор, ведущий научный сотрудник Института прикладных математических исследований КарНЦ РАН; профессор Петрозаводского государственного университета"/>
      <command value="\vspace*">
        <braces>
          <braces>
            <text value="{}"/>
            <text value="4pt"/>
          </braces>
        </braces>
        <braces/>
      </command>
      <command value="\noindent">
        <braces>
          <text value="\noindent"/>
        </braces>
      </command>
      <command value="\textbf">
        <braces>
          <text value="\textbf{}"/>
        </braces>
        <text value="Морозова Юлия Игоревна"/>
      </command>
      <text value="(р."/>
      <command value="\specialsymbol">
        <braces>
          <text value="~---"/>
        </braces>
      </command>
      <text value="научный сотрудник ИПИ РАН"/>
      <command value="\vspace*">
        <braces>
          <braces>
            <text value="{}"/>
            <text value="4pt"/>
          </braces>
        </braces>
        <braces/>
      </command>
      <command value="\noindent">
        <braces>
          <text value="\noindent"/>
        </braces>
      </command>
      <command value="\textbf">
        <braces>
          <text value="\textbf{}"/>
        </braces>
        <text value="Назарова Ирина Александровна"/>
      </command>
      <text value="(р."/>
      <command value="\specialsymbol">
        <braces>
          <text value="~---"/>
        </braces>
      </command>
      <text value="кандидат физико-математических наук, научный сотрудник Вычислительного Центра им."/>
      <text value="А."/>
      <text value="А. Дородницына РАН"/>
      <command value="\vspace*">
        <braces>
          <braces>
            <text value="{}"/>
            <text value="4pt"/>
          </braces>
        </braces>
        <braces/>
      </command>
      <command value="\noindent">
        <braces>
          <text value="\noindent"/>
        </braces>
      </command>
      <command value="\textbf">
        <braces>
          <text value="\textbf{}"/>
        </braces>
        <text value="Разумчик Ростислав Валерьевич"/>
      </command>
      <text value="(р."/>
      <command value="\specialsymbol">
        <braces>
          <text value="~---"/>
        </braces>
      </command>
      <text value="кандидат физико-математических наук, старший научный сотрудник ИПИ РАН"/>
      <command value="\vspace*">
        <braces>
          <braces>
            <text value="{}"/>
            <text value="4pt"/>
          </braces>
        </braces>
        <braces/>
      </command>
      <command value="\noindent">
        <braces>
          <text value="\noindent"/>
        </braces>
      </command>
      <command value="\textbf">
        <braces>
          <text value="\textbf{}"/>
        </braces>
        <text value="Ронжин Александр Федорович"/>
      </command>
      <text value="(р."/>
      <command value="\specialsymbol">
        <braces>
          <text value="~---"/>
        </braces>
      </command>
      <text value="доктор физико-математических наук, профессор, главный научный сотрудник Вычислительного Центра им."/>
      <text value="А."/>
      <text value="А. Дородницына РАН"/>
      <command value="\vspace*">
        <braces>
          <braces>
            <text value="{}"/>
            <text value="4pt"/>
          </braces>
        </braces>
        <braces/>
      </command>
      <command value="\noindent">
        <braces>
          <text value="\noindent"/>
        </braces>
      </command>
      <command value="\textbf">
        <braces>
          <text value="\textbf{}"/>
        </braces>
        <text value="Синицын Игорь Николаевич"/>
      </command>
      <text value="(р."/>
      <command value="\specialsymbol">
        <braces>
          <text value="~---"/>
        </braces>
      </command>
      <text value="доктор технических наук, профессор, заслуженный деятель науки РФ, заведующий отделом ИПИ РАН"/>
      <command value="\vspace*">
        <braces>
          <braces>
            <text value="{}"/>
            <text value="4pt"/>
          </braces>
        </braces>
        <braces/>
      </command>
      <command value="\noindent">
        <braces>
          <text value="\noindent"/>
        </braces>
      </command>
      <command value="\textbf">
        <braces>
          <text value="\textbf{}"/>
        </braces>
        <text value="Сичинава Дмитрий Владимирович"/>
      </command>
      <text value="(р."/>
      <command value="\specialsymbol">
        <braces>
          <text value="~---"/>
        </braces>
      </command>
      <text value="кандидат филологических наук, старший научный сотрудник ИРЯ РАН"/>
      <command value="\vspace*">
        <braces>
          <braces>
            <text value="{}"/>
            <text value="4pt"/>
          </braces>
        </braces>
        <braces/>
      </command>
      <command value="\noindent">
        <braces>
          <text value="\noindent"/>
        </braces>
      </command>
      <command value="\textbf">
        <braces>
          <text value="\textbf{}"/>
        </braces>
        <text value="Смелянский Руслан Леонидович"/>
      </command>
      <text value="(р."/>
      <command value="\specialsymbol">
        <braces>
          <text value="~---"/>
        </braces>
      </command>
      <text value="доктор физико-математических наук, член-корреспондент РАН, профессор кафедры автоматизации систем вычислительных комплексов, заведующий лабораторией факультета вычислительной математики и кибернетики Московского государственного университета им."/>
      <text value="М."/>
      <text value="В. Ломоносова"/>
      <text value="ОБ АВТОРАХ"/>
      <text value="ОБ АВТОРАХ"/>
      <command value="\vspace*">
        <braces>
          <braces>
            <text value="{}"/>
            <text value="4pt"/>
          </braces>
        </braces>
        <braces/>
      </command>
      <command value="\noindent">
        <braces>
          <text value="\noindent"/>
        </braces>
      </command>
      <command value="\textbf">
        <braces>
          <text value="\textbf{}"/>
        </braces>
        <text value="Смелянский Тимофей Русланович"/>
      </command>
      <text value="(р."/>
      <command value="\specialsymbol">
        <braces>
          <text value="~---"/>
        </braces>
      </command>
      <text value="аспирант факультета вычислительной математики и кибернетики Московского государственного университета им."/>
      <text value="М."/>
      <text value="В. Ломоносова"/>
      <command value="\vspace*">
        <braces>
          <braces>
            <text value="{}"/>
            <text value="4pt"/>
          </braces>
        </braces>
        <braces/>
      </command>
      <command value="\noindent">
        <braces>
          <text value="\noindent"/>
        </braces>
      </command>
      <command value="\textbf">
        <braces>
          <text value="\textbf{}"/>
        </braces>
        <text value="Соколов Игорь Анатольевич"/>
      </command>
      <text value="(р."/>
      <command value="\specialsymbol">
        <braces>
          <text value="~---"/>
        </braces>
      </command>
      <text value="академик (действительный член) Российской академии наук; доктор технических наук, директор ИПИ РАН"/>
      <command value="\vspace*">
        <braces>
          <braces>
            <text value="{}"/>
            <text value="4pt"/>
          </braces>
        </braces>
        <braces/>
      </command>
      <command value="\noindent">
        <braces>
          <text value="\noindent"/>
        </braces>
      </command>
      <command value="\textbf">
        <braces>
          <text value="\textbf{}"/>
        </braces>
        <text value="Сомин Николай Владимирович"/>
      </command>
      <text value="(р."/>
      <command value="\specialsymbol">
        <braces>
          <text value="~---"/>
        </braces>
      </command>
      <text value="кандидат физико-математических наук, ведущий научный сотрудник ИПИ РАН"/>
      <command value="\vspace*">
        <braces>
          <braces>
            <text value="{}"/>
            <text value="4pt"/>
          </braces>
        </braces>
        <braces/>
      </command>
      <command value="\noindent">
        <braces>
          <text value="\noindent"/>
        </braces>
      </command>
      <command value="\textbf">
        <braces>
          <text value="\textbf{}"/>
        </braces>
        <text value="Тимофеев Владимир Семенович"/>
      </command>
      <text value="(р."/>
      <command value="\specialsymbol">
        <braces>
          <text value="~---"/>
        </braces>
      </command>
      <text value="доктор технических наук, профессор Новосибирского государственного технического университета"/>
      <command value="\vspace*">
        <braces>
          <braces>
            <text value="{}"/>
            <text value="4pt"/>
          </braces>
        </braces>
        <braces/>
      </command>
      <command value="\noindent">
        <braces>
          <text value="\noindent"/>
        </braces>
      </command>
      <command value="\textbf">
        <braces>
          <text value="\textbf{}"/>
        </braces>
        <text value="Тимофеева Анастасия Юрьевна"/>
      </command>
      <text value="(р."/>
      <command value="\specialsymbol">
        <braces>
          <text value="~---"/>
        </braces>
      </command>
      <text value="кандидат экономических наук, научный сотрудник Новосибирского государственного технического университета"/>
      <command value="\columnbreak"/>
      <command value="\noindent">
        <braces>
          <text value="\noindent"/>
        </braces>
      </command>
      <command value="\textbf">
        <braces>
          <text value="\textbf{}"/>
        </braces>
        <text value="Хапланов Арсений Юрьевич"/>
      </command>
      <text value="(р."/>
      <command value="\specialsymbol">
        <braces>
          <text value="~---"/>
        </braces>
      </command>
      <text value="аспирант кафедры теории вероятностей механико-математического факультета Московского государственного университета им."/>
      <text value="М."/>
      <text value="В. Ломоносова"/>
      <command value="\vspace*">
        <braces>
          <braces>
            <text value="{}"/>
            <text value="4pt"/>
          </braces>
        </braces>
        <braces/>
      </command>
      <command value="\noindent">
        <braces>
          <text value="\noindent"/>
        </braces>
      </command>
      <command value="\textbf">
        <braces>
          <text value="\textbf{}"/>
        </braces>
        <text value="Шалимов Александр Владиславович"/>
      </command>
      <text value="(р."/>
      <command value="\specialsymbol">
        <braces>
          <text value="~---"/>
        </braces>
      </command>
      <text value="программист лаборатории вычислительных комплексов факультета вычислительной математики и кибернетики Московского государственного университета им."/>
      <text value="М."/>
      <text value="В. Ломоносова"/>
      <command value="\vspace*">
        <braces>
          <braces>
            <text value="{}"/>
            <text value="4pt"/>
          </braces>
        </braces>
        <braces/>
      </command>
      <command value="\noindent">
        <braces>
          <text value="\noindent"/>
        </braces>
      </command>
      <command value="\textbf">
        <braces>
          <text value="\textbf{}"/>
        </braces>
        <text value="Шарнин Михаил Михайлович"/>
      </command>
      <text value="(р."/>
      <command value="\specialsymbol">
        <braces>
          <text value="~---"/>
        </braces>
      </command>
      <text value="кандидат технических наук, старший научный сотрудник ИПИ РАН"/>
      <command value="\vspace*">
        <braces>
          <braces>
            <text value="{}"/>
            <text value="4pt"/>
          </braces>
        </braces>
        <braces/>
      </command>
      <command value="\noindent">
        <braces>
          <text value="\noindent"/>
        </braces>
      </command>
      <command value="\textbf">
        <braces>
          <text value="\textbf{}"/>
        </braces>
        <text value="Шестаков Олег Владимирович"/>
      </command>
      <text value="(р."/>
      <command value="\specialsymbol">
        <braces>
          <text value="~---"/>
        </braces>
      </command>
      <text value="доктор физико-математических наук, доцент кафедры математической статистики факультета вычислительной математики и кибернетики Московского"/>
      <command value="\linebreak">
        <braces>
          <text value="\linebreak"/>
        </braces>
      </command>
      <text value="государственного университета им."/>
      <text value="М."/>
      <text value="В. Ломоносова; старший научный сотрудник ИПИ РАН"/>
      <command value="\vspace*">
        <braces>
          <braces>
            <text value="{}"/>
            <text value="4pt"/>
          </braces>
        </braces>
        <braces/>
      </command>
      <command value="\noindent">
        <braces>
          <text value="\noindent"/>
        </braces>
      </command>
      <command value="\textbf">
        <braces>
          <text value="\textbf{}"/>
        </braces>
        <text value="Шоргин Сергей Яковлевич"/>
      </command>
      <text value="(р."/>
      <command value="\specialsymbol">
        <braces>
          <text value="~---"/>
        </braces>
      </command>
      <text value="доктор физико-математических наук, профессор, заместитель директора ИПИ РАН"/>
      <command value="\vspace*">
        <braces>
          <braces>
            <text value="{}"/>
            <text value="4pt"/>
          </braces>
        </braces>
        <braces/>
      </command>
      <command value="\noindent">
        <braces>
          <text value="\noindent"/>
        </braces>
      </command>
      <command value="\textbf">
        <braces>
          <text value="\textbf{}"/>
        </braces>
        <text value="Щеколдин Владислав Юрьевич"/>
      </command>
      <text value="(р."/>
      <command value="\specialsymbol">
        <braces>
          <text value="~---"/>
        </braces>
      </command>
      <text value="кандидат технических наук, доцент Новосибирского государственного технического университета"/>
      <text value="ОБ АВТОРАХ"/>
      <text value="ОБ АВТОРАХ"/>
      <command value="\end">
        <braces>
          <braces>
            <text value="{}"/>
            <text value="multicols"/>
          </braces>
        </braces>
        <braces/>
      </command>
      <command value="\newpage"/>
    </fulltext>
  </paper>
</papers>